mikm/__init__.py
mikm/converter.py
mikm-0.1.2.dist-info/LICENSE
mikm-0.1.2.dist-info/WHEEL
mikm-0.1.2.dist-info/METADATA
mikm-0.1.2.dist-info/RECORD
