Metadata-Version: 2.1
Name: mikm
Version: 0.1.2
Summary: Library for converting miles in kilometers and kilometers in miles.
Home-page: https://github.com/serhii73/mikm
License: MIT
Keywords: converting,kilometers,miles,conversion
Author: serhii73
Author-email: aserhii@protonmail.com
Requires-Python: >=3.7,<4.0
Classifier: Development Status :: 5 - Production/Stable
Classifier: Environment :: Console
Classifier: License :: OSI Approved :: MIT License
Classifier: Operating System :: POSIX
Classifier: Programming Language :: Python
Classifier: Programming Language :: Python :: 3
Classifier: Programming Language :: Python :: 3.7
Project-URL: Repository, https://github.com/serhii73/mikm
